MANIFEST.in
README.rst
pyproject.toml
setup.py
PottsPlayground/Kernels.py
PottsPlayground/Schedules.py
PottsPlayground/__init__.py
PottsPlayground.egg-info/PKG-INFO
PottsPlayground.egg-info/SOURCES.txt
PottsPlayground.egg-info/dependency_links.txt
PottsPlayground.egg-info/requires.txt
PottsPlayground.egg-info/top_level.txt
PottsPlayground/Solvers/Annealables.h
PottsPlayground/Solvers/Annealing.cpp
PottsPlayground/Solvers/ArgsFile.pkl
PottsPlayground/Solvers/Cores.h
PottsPlayground/Solvers/CpuCore.cpp
PottsPlayground/Solvers/GpuCore.cu
PottsPlayground/Solvers/GpuCoreAlt.cpp
PottsPlayground/Solvers/IsingAnnealable.h
PottsPlayground/Solvers/IsingPrecomputeAnnealable.h
PottsPlayground/Solvers/NumCuda.h
PottsPlayground/Solvers/PieceWiseLinear.h
PottsPlayground/Solvers/PottsJitAnnealable.h
PottsPlayground/Solvers/PottsPrecomputeAnnealable.h
PottsPlayground/Solvers/SwapAnnealable.h
PottsPlayground/Solvers/debugBuild.sh
PottsPlayground/Tasks/BaseTask.py
PottsPlayground/Tasks/Binarized.py
PottsPlayground/Tasks/GraphColoring.py
PottsPlayground/Tasks/Ice40Placer.py
PottsPlayground/Tasks/Lattice.py
PottsPlayground/Tasks/MinorEmbedded.py
PottsPlayground/Tasks/TravelingSalesman.py
PottsPlayground/Tasks/__init__.py
PottsPlayground/Test/TestAnneal.py
PottsPlayground/Test/TestBaseTask.py
PottsPlayground/Test/TestBinarized.py
PottsPlayground/Test/TestColoring.py
PottsPlayground/Test/TestExamples.py
PottsPlayground/Test/TestMinorEmbedded.py
PottsPlayground/Test/TestSchedules.py
PottsPlayground/Test/TestTsp.py
PottsPlayground/Test/__main__.py