Metadata-Version: 2.4
Name: PottsPlayground
Version: 0.3.0
Summary: For creating and solving Potts-model representations of combinatorial optimization problems
Author-email: William Whitehead <williamwhitehead@ucsb.edu>
Project-URL: documentation, https://williamow.github.io/PottsPlayground/index.html
Project-URL: source, https://github.com/williamow/PottsPlayground/
Requires-Python: >=3.6
Requires-Dist: matplotlib>=0.0.0
Requires-Dist: networkx>=2.0
Requires-Dist: numpy>=1.17.0
